totororequests/__init__.py
totororequests/totoro.py
totororequests-1.2.0.dist-info/LICENSE
totororequests-1.2.0.dist-info/METADATA
totororequests-1.2.0.dist-info/WHEEL
totororequests-1.2.0.dist-info/top_level.txt
totororequests-1.2.0.dist-info/RECORD
