Metadata-Version: 2.1
Name: totororequests
Version: 1.2.0
Summary: Smart Python module for sending HTTP(S) requests through Tor network
Home-page: https://github.com/ray0be/totororequests
Author: Victor Paynat-Sautivet
Author-email: contact@ray0.be
License: UNKNOWN
Platform: UNKNOWN
Classifier: Programming Language :: Python :: 3
Classifier: License :: OSI Approved :: MIT License
Classifier: Operating System :: Unix
Requires-Python: >=3.6
Requires-Dist: requests
Requires-Dist: stem
Requires-Dist: fake-useragent
